CHANGELOG.md
COPYING
MANIFEST.in
README.md
cmakedoc.py
setup.py
cmakedoc.egg-info/PKG-INFO
cmakedoc.egg-info/SOURCES.txt
cmakedoc.egg-info/dependency_links.txt
cmakedoc.egg-info/entry_points.txt
cmakedoc.egg-info/top_level.txt