Metadata-Version: 1.1
Name: cmakedoc
Version: 1.0.1
Summary: cmakedoc makes it easier to search CMake reference documentation.
